src/__init__.py
src/__main__.py
pydadjoke-1.0.0.dist-info/LICENSE
pydadjoke-1.0.0.dist-info/METADATA
pydadjoke-1.0.0.dist-info/WHEEL
pydadjoke-1.0.0.dist-info/entry_points.txt
pydadjoke-1.0.0.dist-info/top_level.txt
pydadjoke-1.0.0.dist-info/RECORD
