Metadata-Version: 2.1
Name: pydadjoke
Version: 1.0.0
Summary: CLI to call the icanhazdadjoke API and returns a dad joke
Home-page: https://github.com/jwood803/pydadjoke
License: MIT
Platform: UNKNOWN
Requires-Dist: fire
Requires-Dist: requests
